beetsplug/__init__.py
beetsplug/yapl.py
beets_yapl-0.1.2.dist-info/LICENSE
beets_yapl-0.1.2.dist-info/METADATA
beets_yapl-0.1.2.dist-info/WHEEL
beets_yapl-0.1.2.dist-info/top_level.txt
beets_yapl-0.1.2.dist-info/RECORD
