Metadata-Version: 2.1
Name: beets-yapl
Version: 0.1.2
Summary: beets plugin to handle yaml playlists
Home-page: http://www.github.com/nichobi/beets-yapl
Author: Nicholas Boyd Isacsson
Author-email: nicholas@isacsson.se
License: GPL3
Platform: ALL
Classifier: Topic :: Multimedia :: Sound/Audio
Classifier: Topic :: Multimedia :: Sound/Audio :: Players :: MP3
Classifier: License :: OSI Approved :: GNU General Public License v3 (GPLv3)
Classifier: Environment :: Console
Classifier: Programming Language :: Python :: 3
License-File: LICENSE
Requires-Dist: beets (>=1.4.7)
